c2c/__init__.py
c2c/c2c.py
c2c-1.1.0.dist-info/METADATA
c2c-1.1.0.dist-info/WHEEL
c2c-1.1.0.dist-info/entry_points.txt
c2c-1.1.0.dist-info/licenses/LICENSE
c2c-1.1.0.dist-info/RECORD
