Metadata-Version: 2.4
Name: c2c
Version: 1.1.0
Summary: Convert directory structure into a single text file while respecting .gitignore rules
Project-URL: Source, https://github.com/ykawataki/c2c
Author-email: Yoshikazu Kawataki <y.kawataki@gmail.com>
License-File: LICENSE
Classifier: Development Status :: 3 - Alpha
Classifier: Environment :: Console
Classifier: License :: OSI Approved :: MIT License
Classifier: Operating System :: OS Independent
Classifier: Programming Language :: Python :: 3
Classifier: Topic :: Software Development :: Libraries :: Python Modules
Classifier: Topic :: Utilities
Requires-Python: >=3.7
Requires-Dist: gitignore-filter>=0.2.2
